mqtt_processor/__init__.py
mqtt_processor/client.py
mqtt_processor/config.py
mqtt_processor/db_connector.py
mqtt_processor/processor.py
mqtt_processor/utils.py
mqtt_processor-0.1.0.dist-info/licenses/LICENSE
mqtt_processor-0.1.0.dist-info/METADATA
mqtt_processor-0.1.0.dist-info/WHEEL
mqtt_processor-0.1.0.dist-info/top_level.txt
mqtt_processor-0.1.0.dist-info/RECORD
