Metadata-Version: 2.4
Name: mqtt_processor
Version: 0.1.0
Summary: A Python package for real-time MQTT data processing with database integration
Home-page: https://github.com/Deep26011999/mqtt-data-processor
Author: Deep Shikhar Singh
Author-email: deepshikharsingh@gmail.com
Classifier: Programming Language :: Python :: 3
Classifier: License :: OSI Approved :: MIT License
Classifier: Operating System :: OS Independent
Requires-Python: >=3.7
License-File: LICENSE
Requires-Dist: paho-mqtt==2.1.0
Requires-Dist: psycopg2==2.9.10
Requires-Dist: python-dotenv==1.1.0
Requires-Dist: dnspython==2.7.0
Requires-Dist: pytest==7.0.0
Dynamic: author
Dynamic: author-email
Dynamic: classifier
Dynamic: description
Dynamic: description-content-type
Dynamic: home-page
Dynamic: license-file
Dynamic: requires-dist
Dynamic: requires-python
Dynamic: summary
